myodan_tools/__init__.py
myodan_tools/__main__.py
myodan_tools/downloader/mediafire.py
myodan_tools/extractor/mrcong.py
myodan_tools/main.py
myodan_tools-0.0.9.dist-info/entry_points.txt
myodan_tools-0.0.9.dist-info/WHEEL
myodan_tools-0.0.9.dist-info/METADATA
myodan_tools-0.0.9.dist-info/RECORD
