Metadata-Version: 2.1
Name: myodan-tools
Version: 0.0.9
Summary: 
Author: Jongho Hong
Author-email: myodan@pm.me
Requires-Python: >=3.10.0,<3.11
Classifier: Programming Language :: Python :: 3
Classifier: Programming Language :: Python :: 3.10
Requires-Dist: Flask (>=2.2.0,<3.0.0)
Requires-Dist: beautifulsoup4 (>=4.12.2,<5.0.0)
Requires-Dist: lxml (>=4.9.2,<5.0.0)
Requires-Dist: numpy (>=1.22.2,<2.0.0)
Requires-Dist: replit (>=3.2.4,<4.0.0)
Requires-Dist: requests (>=2.28.2,<3.0.0)
Requires-Dist: six (>=1.16.0,<2.0.0)
Requires-Dist: typer[all] (>=0.7.0,<0.8.0)
Requires-Dist: urllib3 (>=1.26.12,<2.0.0)
